bybit_bulk_downloader/__init__.py
bybit_bulk_downloader/downloader.py
bybit_bulk_downloader-1.2.4.dist-info/licenses/LICENSE
bybit_bulk_downloader-1.2.4.dist-info/METADATA
bybit_bulk_downloader-1.2.4.dist-info/WHEEL
bybit_bulk_downloader-1.2.4.dist-info/top_level.txt
bybit_bulk_downloader-1.2.4.dist-info/RECORD
