Metadata-Version: 2.4
Name: bybit-bulk-downloader
Version: 1.2.4
Summary:  Python library to efficiently and concurrently download historical data files from Bybit. Supports all asset types (spot, USDT-M, COIN-M, options) and all data frequencies.
Author: aoki-h-jp
Author-email: hirotaka.aoki@solopreneurs.tech
License: MIT
License-File: LICENSE
Requires-Dist: requests
Requires-Dist: rich
Requires-Dist: pytest
Requires-Dist: beautifulsoup4
Requires-Dist: pybit
Dynamic: author
Dynamic: author-email
Dynamic: license
Dynamic: license-file
Dynamic: requires-dist
Dynamic: summary
